Workbook

Sheet Lab1
A1: SN | B1: Year | C1: Net Yearly CashFlow (Rs.) | D1: Cummulative CashFlow | E1: Discount Factor (@ 6%) | F1: Discounted CastFlow | G1: Cummulative Discounted CashFlow
A2: 1 | B2: 0 | C2: -290000 | D2: =C2 -> -290000 | E2: =1/(1+6/100)^B2 -> 1 | F2: =E2*C2 -> -290000 | G2: =F2 -> -290000
A3: 2 | B3: 1 | C3: 70000 | D3: =D2+C3 -> -220000 | E3: =1/(1+6/100)^B3 -> 0.94339623 | F3: =E3*C3 -> 66037.736 | G3: =G2+F3 -> -223962.26
A4: 3 | B4: 2 | C4: 70000 | D4: =D3+C4 -> -150000 | E4: =1/(1+6/100)^B4 -> 0.88999644 | F4: =E4*C4 -> 62299.751 | G4: =G3+F4 -> -161662.51
A5: 4 | B5: 3 | C5: 70000 | D5: =D4+C5 -> -80000 | E5: =1/(1+6/100)^B5 -> 0.83961928 | F5: =E5*C5 -> 58773.35 | G5: =G4+F5 -> -102889.16
A6: 5 | B6: 4 | C6: 70000 | D6: =D5+C6 -> -10000 | E6: =1/(1+6/100)^B6 -> 0.79209366 | F6: =E6*C6 -> 55446.556 | G6: =G5+F6 -> -47442.607
A7: 6 | B7: 5 | C7: 70000 | D7: =D6+C7 -> 60000 | E7: =1/(1+6/100)^B7 -> 0.74725817 | F7: =E7*C7 -> 52308.072 | G7: =G6+F7 -> 4865.465
A8: No. of Year | B8: =COUNT(B3:B7) -> 5 | C8: Total Benefit :
C9: =SUM(C3:C7) -> 350000
C10: Total Investment / Cost :
C11: =ABS(C2) -> 290000
A14: NetProfit: | B14: =C9-C11 -> 60000 | C14: % | H14: Net Profit = Total Benefit - Total Cost
A15: Net ROI : | B15: =(B14/ABS(C11))*100 -> 20.689655 | C15: % | H15: ROI = NetProfilt / Total Investment * 100%
A16: YearlyROI : | B16: =(B14/B8)/ABS(C11)*100 -> 4.137931 | C16: % | H16: Yearly ROI = Avarege Profit Per Year / Total Investment *100 %
A17: PayBackPeriod: | B17: =B6+(ABS(D6)/C7) -> 4.1428571 | C17: Year | H17: PayBack Period = Year(Last Negative) + (Unrecovered Cash at start of the year/Yearly CashFlow)
A18: NPV : | B18: =SUM(F2:F7) -> 4865.465 | H18: Discount Factor = 1/(1+6)^Year
A19: Discounted PayBack Period: | B19: =4+(ABS(G6)/F6) -> 4.8556457 | C19: Year | H19: Discounted CashFlow = DiscountFactor / CashFlow
A20: IRR : | B20: =IRR(C2:C7,10) -> 0.066146074 | H20: NPV = Sum(Discounted CashFlow)
A21: PW of Benefit : | B21: =SUM(F3:F7) -> 294865.46 | H21: PW of Benefit = Sum(Discounted CashFlow)
A22: PW of Cost: | B22: =F2 -> -290000 | H22: PW of Cost = Negative Cashflow
A23: B-C Ratio : | B23: =B21/ABS(B22) -> 1.0167775 | C23: =IF(B23>1,">1 means Project is Acceptable", "<1 means Project is not Acceptable") -> >1 means Project is Acceptable

Sheet Lab3
C2: Activity | D2: Duration | E2: PerdayRate | F2: TotalCost
C3: A | D3: 2 | E3: 300 | F3: =E3*D3 -> 600
C4: B | D4: 3 | E4: 400 | F4: =E4*D4 -> 1200
C5: C | D5: 3 | E5: 400 | F5: =E5*D5 -> 1200
C6: D | D6: 2 | E6: 200 | F6: =E6*D6 -> 400
C7: E | D7: 3 | E7: 100 | F7: =E7*D7 -> 300
B10: ProgressMonitored(FieldReport) at day 7

Sheet Lab3FieldReport
B2: Field Report At The Enf Of Day 7
B3: SN | C3: Activity | D3: Actual % Completed | E3: IncurredCost
B4: 1 | C4: A | D4: 100 | E4: 600
B5: 2 | C5: B | D5: 100 | E5: 1400
B6: 3 | C6: C | D6: 33 | E6: 500
B7: 4 | C7: D | D7: 50 | E7: 200
B8: 5 | C8: E | D8: 0 | E8: 0

Sheet Lab3EVA Calculation
A1: Activity | B1: ACWP | C1: BCWP | D1: Required % Complete at Day 7 | E1: BCWS
A2: A | B2: =Lab3FieldReport!E4 -> 600 | C2: =Lab3FieldReport!D4*'Lab3'!F3/100 -> 600 | D2: 100 | E2: =D2*'Lab3'!F3/100 -> 600
A3: B | B3: =Lab3FieldReport!E5 -> 1400 | C3: =Lab3FieldReport!D5*'Lab3'!F4/100 -> 1200 | D3: 100 | E3: =D3*'Lab3'!F4/100 -> 1200
A4: C | B4: =Lab3FieldReport!E6 -> 500 | C4: =Lab3FieldReport!D6*'Lab3'!F5/100 -> 396 | D4: 66 | E4: =D4*'Lab3'!F5/100 -> 792
A5: D | B5: =Lab3FieldReport!E7 -> 200 | C5: =Lab3FieldReport!D7*'Lab3'!F6/100 -> 200 | D5: 100 | E5: =D5*'Lab3'!F6/100 -> 400
A6: E | B6: =Lab3FieldReport!E8 -> 0 | C6: =Lab3FieldReport!D8*'Lab3'!F7/100 -> 0 | D6: 0 | E6: =D6*'Lab3'!F7/100 -> 0
A7: Sum | B7: =SUM(B2:B6) -> 2700 | C7: =SUM(C2:C6) -> 2396 | E7: =SUM(E2:E6) -> 2992
B9: CPI | C9: BCWP/ACWP | D9: =C7/B7 -> 0.88740741
B10: SPI | C10: BCWP/BCWS | D10: =C7/E7 -> 0.80080214
B11: CV | C11: BCWP-ACWP | D11: =C7-B7 -> -304
B12: SV | C12: BCWP-BCWS | D12: =C7-E7 -> -596
C14: Conclusion:
D15: =IF(D9>1,"The Project is on Budget","The Project is Over Budget") -> The Project is Over Budget
D16: =IF(D10>1,"The Project is on Schedule","The Project is Behind Schedule") -> The Project is Behind Schedule
